snowflake_keypair_helper/__init__.py
snowflake_keypair_helper/api.py
snowflake_keypair_helper/cli.py
snowflake_keypair_helper/con_utils.py
snowflake_keypair_helper/constants.py
snowflake_keypair_helper/crypto_utils.py
snowflake_keypair_helper/dataclass_utils.py
snowflake_keypair_helper/env_utils.py
snowflake_keypair_helper/init_state_utils.py
snowflake_keypair_helper/tests/conftest.py
snowflake_keypair_helper/tests/test_cli.py
snowflake_keypair_helper/tests/test_con_utils.py
snowflake_keypair_helper/tests/test_snowflake_keypair.py
snowflake_keypair_helper-0.1.0.dist-info/WHEEL
snowflake_keypair_helper-0.1.0.dist-info/entry_points.txt
snowflake_keypair_helper-0.1.0.dist-info/METADATA
snowflake_keypair_helper-0.1.0.dist-info/RECORD
