Metadata-Version: 2.3
Name: snowflake-keypair-helper
Version: 0.1.0
Summary: A library for creating, managing and using keypairs to authenticate to Snowflake
Author: Dan Lovell
Author-email: Dan Lovell <dan@letsql.com>
License:                                  Apache License
Requires-Dist: adbc-driver-snowflake>=1.8.0
Requires-Dist: click>=8.3.0
Requires-Dist: snowflake-connector-python>=3.17.4
Requires-Dist: strenum>=0.4.15 ; python_full_version < '3.11'
Requires-Dist: toolz>=1.0.0
Maintainer: Dan Lovell, Daniel Mesejo
Maintainer-email: Dan Lovell <dan@letsql.com>, Daniel Mesejo <mesejo@letsql.com>
Requires-Python: >=3.10
Project-URL: Issues, https://github.com/xorq-labs/snowflake-keypair-helper/issues
Project-URL: Repository, https://github.com/xorq-labs/snowflake-keypair-helper/
